aplicacion_ventas/__init__.py
aplicacion_ventas/descuentos.py
aplicacion_ventas/exceptions.py
aplicacion_ventas/gestor_ventas.py
aplicacion_ventas/impuestos.py
aplicacion_ventas/precios.py
aplicacion_ventas_jchinchilla-0.1.1.dist-info/licenses/LICENCE
tests_/__init__.py
tests_/test_aplicacion_ventas.py
aplicacion_ventas_jchinchilla-0.1.1.dist-info/METADATA
aplicacion_ventas_jchinchilla-0.1.1.dist-info/WHEEL
aplicacion_ventas_jchinchilla-0.1.1.dist-info/top_level.txt
aplicacion_ventas_jchinchilla-0.1.1.dist-info/RECORD
